crudlib/__init__.py
crudlib/base.py
crudlib/config.py
crudlib/mariadb.py
crudlib/mysql.py
crudlib/sqlite.py
crudlib/uri.py
tests/__init__.py
tests/test_mysql.py
tests/test_uri.py
crudlib-1.2.2.dist-info/LICENSE
crudlib-1.2.2.dist-info/METADATA
crudlib-1.2.2.dist-info/WHEEL
crudlib-1.2.2.dist-info/top_level.txt
crudlib-1.2.2.dist-info/RECORD
